velu/__init__.py
velu/printvelu.py
velu-0.2.dist-info/LICENSE
velu-0.2.dist-info/METADATA
velu-0.2.dist-info/WHEEL
velu-0.2.dist-info/top_level.txt
velu-0.2.dist-info/RECORD
