Metadata-Version: 2.1
Name: velu
Version: 0.2
Summary: I am attempting to create a Python Package
Home-page: https://github.com/velu4689a/velu
Author: Pythonic Velu
Author-email: manoharvelmurugan@gmail.com
License: MIT
Platform: UNKNOWN
Classifier: Programming Language :: Python :: 3
Classifier: License :: OSI Approved :: MIT License
Classifier: Operating System :: OS Independent
